metro_integrase
