Metadata-Version: 2.1
Name: metro-integrase
Version: 0.0.8
Summary: A Python wrapper for the Metro Reviews API
Author: Rootspring
Author-email: cheesycod@outlook.com
